g910_gkeys/__init__.py
g910_gkeys/g910_gkeys.py
g910_gkeys/layout_config_helpers.py
g910_gkeys/data_mappers/__init__.py
g910_gkeys/data_mappers/bytearrays.py
g910_gkeys/data_mappers/char_uinput_mapper.py
g910_gkeys/data_mappers/supported_configs.py
g910_gkeys/data_mappers/supported_devices.py
g910_gkeys/data_mappers/uinput_all_keys.py
g910_gkeys/lib/__init__.py
g910_gkeys/lib/keyboard.py
g910_gkeys/lib/usb_device.py
g910_gkeys/misc/__init__.py
g910_gkeys/misc/config.py
g910_gkeys/misc/helper.py
g910_gkeys/misc/logger.py
g910_gkeys/misc/memory_leds.py
g910_gkeys/misc/notify.py
g910_gkeys-0.4.2.dist-info/LICENSE
g910_gkeys-0.4.2.dist-info/METADATA
g910_gkeys-0.4.2.dist-info/WHEEL
g910_gkeys-0.4.2.dist-info/entry_points.txt
g910_gkeys-0.4.2.dist-info/top_level.txt
g910_gkeys-0.4.2.dist-info/RECORD
