Metadata-Version: 2.1
Name: g910-gkeys
Version: 0.4.2
Summary: Support for Logitech G910 GKeys on GNU/Linux
Author-email: Jan Šubelj <jan.subelj010@gmail.com>, Marcel Grolms <support@suabo.de>
License: GNU GENERAL PUBLIC LICENSE
Project-URL: Homepage, https://github.com/JSubelj/g910-gkey-macro-support
Project-URL: Bug Tracker, https://github.com/JSubelj/g910-gkey-macro-support/issues
Keywords: logitech,keyboard,gkey,G910,G915,G815,G710,G510
Classifier: Development Status :: 4 - Beta
Classifier: License :: OSI Approved :: GNU General Public License v3 (GPLv3)
Classifier: Programming Language :: Python
Classifier: Programming Language :: Python :: 3
Classifier: Programming Language :: Python :: 3.7
Classifier: Programming Language :: Python :: 3.8
Classifier: Programming Language :: Python :: 3.9
Classifier: Programming Language :: Python :: 3.11
Requires-Python: >=3.7
License-File: LICENSE
Requires-Dist: python-uinput ==0.11.2
Requires-Dist: pyusb ==1.2.1
